vsearcher/__init__.py
vsearcher/_config/__init__.py
vsearcher/_config/args.py
vsearcher/_config/path.py
vsearcher/_core/__init__.py
vsearcher/_core/decorate.py
vsearcher/_core/sim.py
vsearcher/_core/type.py
vsearcher/_core/utils.py
vsearcher/_core/video.py
vsearcher/_core/vo.py
vsearcher-0.2.16.dist-info/LICENSE
vsearcher-0.2.16.dist-info/METADATA
vsearcher-0.2.16.dist-info/WHEEL
vsearcher-0.2.16.dist-info/top_level.txt
vsearcher-0.2.16.dist-info/RECORD
