Metadata-Version: 2.1
Name: vsearcher
Version: 0.2.16
Summary: 支持视频内容检索和课件自动生成的库
Home-page: https://gitee.com/breath57/vsearch/tree/0.2.16-pypi
Author: breath
Author-email: 1498408920@qq.com
Maintainer: breath
Keywords: video,search,video search,courseware,ocr
Classifier: Programming Language :: Python :: 3
Classifier: License :: OSI Approved :: MIT License
Classifier: Operating System :: OS Independent
Requires-Python: >=3.9
License-File: LICENSE
Requires-Dist: filetype (>=1.0.13)
Requires-Dist: img2pdf (>=0.4.4)
Requires-Dist: jieba (>=0.42.1)
Requires-Dist: numpy (>=1.22.4)
Requires-Dist: opencv-python (>=4.5.5.64)
Requires-Dist: paddleocr (>=2.5)
Requires-Dist: Pillow (>=9.1.1)
